simpleseleniumwrapper/__init__.py
simpleseleniumwrapper/actionChains.py
simpleseleniumwrapper/alerts.py
simpleseleniumwrapper/baseImports.py
simpleseleniumwrapper/elementLocation.py
simpleseleniumwrapper/proxyAuth.py
simpleseleniumwrapper/webDriver.py
simpleseleniumwrapper/webElement.py
simpleseleniumwrapper/webdriverManager.py
simpleseleniumwrapper-0.3.4.dist-info/METADATA
simpleseleniumwrapper-0.3.4.dist-info/WHEEL
simpleseleniumwrapper-0.3.4.dist-info/top_level.txt
simpleseleniumwrapper-0.3.4.dist-info/RECORD
